mayhap/__init__.py
mayhap/decorators.py
mayhap/distributions.py
mayhap/utils.py
mayhap-0.2.0.dist-info/licenses/LICENSE
mayhap-0.2.0.dist-info/METADATA
mayhap-0.2.0.dist-info/WHEEL
mayhap-0.2.0.dist-info/top_level.txt
mayhap-0.2.0.dist-info/RECORD
