Metadata-Version: 2.4
Name: mayhap
Version: 0.2.0
Summary: Where your functions may happen... or not. Embrace the uncertainty in your code execution!
Author: Vaadeendra Kumar Burra
License: GPL-3.0-only
Project-URL: Homepage, https://github.com/Vaadee/mayhap
Project-URL: Bug Tracker, https://github.com/Vaadee/mayhap/issues
Project-URL: Documentation, https://github.com/Vaadee/mayhap/blob/main/README.md
Project-URL: Source Code, https://github.com/Vaadee/mayhap
Keywords: randomness,decorator,probability,uncertainty
Classifier: Development Status :: 3 - Alpha
Classifier: Intended Audience :: Developers
Classifier: Programming Language :: Python :: 3
Classifier: License :: OSI Approved :: GNU General Public License v3 (GPLv3)
Classifier: Topic :: Software Development :: Libraries :: Python Modules
Requires-Python: >=3.11
License-File: LICENSE
Requires-Dist: pydantic>=2.11.1
Dynamic: license-file
